pyinfoblox
