Metadata-Version: 1.1
Name: pyinfoblox
Version: 0.1.3
Summary: Infoblox WAPI module for Python
Home-page: https://github.com/dnaeon/pyinfoblox
Author: Marin Atanasov Nikolov
Author-email: dnaeon@gmail.com
License: BSD
Download-URL: https://github.com/dnaeon/pyinfoblox/releases
Platform: UNKNOWN
